backlinks_mcp-0.1.7.dist-info/METADATA
backlinks_mcp-0.1.7.dist-info/WHEEL
backlinks_mcp-0.1.7.dist-info/entry_points.txt
backlinks_mcp-0.1.7.dist-info/licenses/LICENSE
backlinks_mcp/__init__.py
backlinks_mcp/server.py
backlinks_mcp-0.1.7.dist-info/RECORD
