Metadata-Version: 2.1
Name: backlinks-mcp
Version: 0.1.7
Summary: A MCP service for retrieving backlink information for any domain using Ahrefs' data
Author-Email: cnych <ych_1024@163.com>
License: MIT
Classifier: Programming Language :: Python :: 3
Classifier: License :: OSI Approved :: MIT License
Classifier: Operating System :: OS Independent
Project-URL: Homepage, https://github.com/cnych/backlinks-mcp
Project-URL: Bug Tracker, https://github.com/cnych/backlinks-mcp/issues
Requires-Python: >=3.8
Requires-Dist: fastmcp>=2.0.0
Requires-Dist: requests>=2.32.3
